tbr/__init__.py
tbr/py.typed
tbr/analysis/__init__.py
tbr/analysis/diagnostics.py
tbr/analysis/incremental.py
tbr/analysis/performance.py
tbr/analysis/subinterval.py
tbr/analysis/summary.py
tbr/core/__init__.py
tbr/core/diagnostics.py
tbr/core/effects.py
tbr/core/inference.py
tbr/core/model.py
tbr/core/posterior.py
tbr/core/prediction.py
tbr/core/regression.py
tbr/core/results.py
tbr/functional/__init__.py
tbr/functional/tbr_functions.py
tbr/utils/__init__.py
tbr/utils/constants.py
tbr/utils/datetime_utils.py
tbr/utils/exceptions.py
tbr/utils/export.py
tbr/utils/performance.py
tbr/utils/preprocessing.py
tbr/utils/structure_validation.py
tbr/utils/validation.py
tbr/visualization/__init__.py
tbr-0.1.5.dist-info/licenses/LICENSE
tbr-0.1.5.dist-info/METADATA
tbr-0.1.5.dist-info/WHEEL
tbr-0.1.5.dist-info/top_level.txt
tbr-0.1.5.dist-info/RECORD
