Metadata-Version: 2.4
Name: tbr
Version: 0.1.5
Summary: A comprehensive, domain-agnostic Python package for Time-Based Regression (TBR) analysis
Author-email: Ido Hirsh <idohirsh@users.noreply.github.com>
Maintainer-email: Ido Hirsh <idohirsh@users.noreply.github.com>
License: BSD-3-Clause
Project-URL: Homepage, https://github.com/idohi/tbr
Project-URL: Repository, https://github.com/idohi/tbr
Project-URL: Documentation, https://tbr.readthedocs.io/
Project-URL: Bug Tracker, https://github.com/idohi/tbr/issues
Project-URL: Changelog, https://github.com/idohi/tbr/blob/main/CHANGELOG.md
Keywords: time-based-regression,tbr,causal-inference,statistics,data-science,regression-analysis,treatment-control,time-series
Classifier: Development Status :: 4 - Beta
Classifier: Intended Audience :: Developers
Classifier: Intended Audience :: Science/Research
Classifier: Operating System :: OS Independent
Classifier: Programming Language :: Python :: 3
Classifier: Programming Language :: Python :: 3.8
Classifier: Programming Language :: Python :: 3.9
Classifier: Programming Language :: Python :: 3.10
Classifier: Programming Language :: Python :: 3.11
Classifier: Programming Language :: Python :: 3.12
Classifier: Topic :: Scientific/Engineering
Classifier: Topic :: Scientific/Engineering :: Mathematics
Classifier: Topic :: Software Development :: Libraries :: Python Modules
Classifier: Typing :: Typed
Requires-Python: >=3.8
License-File: LICENSE
Requires-Dist: pandas<2.0.0,>=1.5.0; python_version < "3.9"
Requires-Dist: pandas~=2.0.0; python_version >= "3.9"
Requires-Dist: numpy<1.25.0,>=1.21.0; python_version < "3.9"
Requires-Dist: numpy~=1.24.0; python_version >= "3.9"
Requires-Dist: scipy<1.11.0,>=1.9.0; python_version < "3.9"
Requires-Dist: scipy~=1.10.0; python_version >= "3.9"
Requires-Dist: statsmodels<0.15.0,>=0.13.0; python_version < "3.9"
Requires-Dist: statsmodels~=0.14.0; python_version >= "3.9"
Requires-Dist: lazy_loader>=0.1
Requires-Dist: psutil>=5.9.0
Provides-Extra: dev
Requires-Dist: pytest>=7.0.0; extra == "dev"
Requires-Dist: pytest-cov>=4.0.0; extra == "dev"
Requires-Dist: pytest-xdist>=3.0.0; extra == "dev"
Requires-Dist: black>=23.0.0; extra == "dev"
Requires-Dist: isort>=5.12.0; extra == "dev"
Requires-Dist: ruff>=0.1.0; extra == "dev"
Requires-Dist: mypy>=1.0.0; extra == "dev"
Requires-Dist: pre-commit>=3.0.0; extra == "dev"
Requires-Dist: tox>=4.0.0; extra == "dev"
Requires-Dist: pydocstyle[toml]>=6.3.0; extra == "dev"
Requires-Dist: interrogate>=1.5.0; extra == "dev"
Requires-Dist: vulture>=2.7; extra == "dev"
Requires-Dist: psutil>=5.9.0; extra == "dev"
Provides-Extra: docs
Requires-Dist: sphinx>=6.0.0; extra == "docs"
Requires-Dist: sphinx-rtd-theme>=1.2.0; extra == "docs"
Provides-Extra: examples
Requires-Dist: jupyter>=1.0.0; extra == "examples"
Requires-Dist: matplotlib~=3.7.0; extra == "examples"
Requires-Dist: seaborn~=0.12.0; extra == "examples"
Dynamic: license-file
